aiorestapi/__init__.py
aiorestapi/routers.py
aiorestapi/views.py
aiorestapi-0.1.2.dist-info/LICENSE
aiorestapi-0.1.2.dist-info/METADATA
aiorestapi-0.1.2.dist-info/WHEEL
aiorestapi-0.1.2.dist-info/top_level.txt
aiorestapi-0.1.2.dist-info/RECORD
